manage/__init__.py
manage/__main__.py
manage/auto_import.py
manage/cli.py
manage/commands_collector.py
manage/template.py
manage-0.1.15.dist-info/AUTHORS.rst
manage-0.1.15.dist-info/LICENSE
manage-0.1.15.dist-info/METADATA
manage-0.1.15.dist-info/WHEEL
manage-0.1.15.dist-info/entry_points.txt
manage-0.1.15.dist-info/top_level.txt
manage-0.1.15.dist-info/RECORD
