Metadata-Version: 2.1
Name: manage
Version: 0.1.15
Summary: Command Line Manager + Interactive Shell for Python Projects
Home-page: https://github.com/pthon-manage/manage
Author: Bruno Rocha
Author-email: rochacbruno@gmail.com
License: ISC license
Keywords: manage
Platform: UNKNOWN
Classifier: Development Status :: 2 - Pre-Alpha
Classifier: Intended Audience :: Developers
Classifier: License :: OSI Approved :: ISC License (ISCL)
Classifier: Natural Language :: English
Classifier: Programming Language :: Python :: 3.6
Classifier: Programming Language :: Python :: 3.7
Classifier: Programming Language :: Python :: 3.8
Classifier: Programming Language :: Python :: 3.9
